mineru_cli/cli.py
mineru_cli/draw_bbox.py
mineru_cli/pdf_utils.py
mineru_cli-0.1.1.dist-info/licenses/LICENSE
venv/bin/dumppdf.py
venv/bin/jp.py
venv/bin/pdf2txt.py
mineru_cli-0.1.1.dist-info/METADATA
mineru_cli-0.1.1.dist-info/WHEEL
mineru_cli-0.1.1.dist-info/entry_points.txt
mineru_cli-0.1.1.dist-info/top_level.txt
mineru_cli-0.1.1.dist-info/RECORD
