Metadata-Version: 2.4
Name: mineru-cli
Version: 0.1.1
Summary: Command-line utility to parse documents using VLM backends (vlm-sglang-engine or vlm-sglang-client)
Author-email: DotIN13 <tzhang3@uchicago.edu>
License: GNU AFFERO GENERAL PUBLIC LICENSE  
Classifier: Programming Language :: Python :: 3
Classifier: License :: OSI Approved :: MIT License
Classifier: Operating System :: OS Independent
License-File: LICENSE
Requires-Dist: mineru[all]>=2.0.6
Requires-Dist: loguru
Requires-Dist: pyyaml
Requires-Dist: numpy
Requires-Dist: pymupdf
Dynamic: license-file
